{
    "pages": [
        {
            "number": 1,
            "labels": [
                {
                    "top": 42,
                    "left": 197,
                    "width": 347,
                    "height": 18,
                    "label_type": 0
                },
                {
                    "top": 765,
                    "left": 226,
                    "width": 161,
                    "height": 9,
                    "label_type": 0
                },
                {
                    "top": 755,
                    "left": 61,
                    "width": 13,
                    "height": 11,
                    "label_type": 0
                },
                {
                    "top": 666,
                    "left": 55,
                    "width": 239,
                    "height": 65,
                    "label_type": 0
                },
                {
                    "top": 249,
                    "left": 73,
                    "width": 149,
                    "height": 9,
                    "label_type": 0
                },
                {
                    "top": 260,
                    "left": 73,
                    "width": 183,
                    "height": 9,
                    "label_type": 0
                },
                {
                    "top": 270,
                    "left": 73,
                    "width": 203,
                    "height": 186,
                    "label_type": 0
                },
                {
                    "top": 458,
                    "left": 90,
                    "width": 186,
                    "height": 19,
                    "label_type": 0
                },
                {
                    "top": 491,
                    "left": 55,
                    "width": 239,
                    "height": 118,
                    "label_type": 0
                },
                {
                    "top": 612,
                    "left": 55,
                    "width": 239,
                    "height": 30,
                    "label_type": 0
                },
                {
                    "top": 249,
                    "left": 318,
                    "width": 239,
                    "height": 42,
                    "label_type": 0
                },
                {
                    "top": 293,
                    "left": 318,
                    "width": 239,
                    "height": 151,
                    "label_type": 0
                },
                {
                    "top": 447,
                    "left": 318,
                    "width": 239,
                    "height": 75,
                    "label_type": 0
                },
                {
                    "top": 534,
                    "left": 318,
                    "width": 235,
                    "height": 21,
                    "label_type": 0
                },
                {
                    "top": 567,
                    "left": 318,
                    "width": 239,
                    "height": 164,
                    "label_type": 0
                },
                {
                    "top": 81,
                    "left": 217,
                    "width": 311,
                    "height": 97,
                    "label_type": 0
                },
                {
                    "top": 199,
                    "left": 217,
                    "width": 169,
                    "height": 16,
                    "label_type": 0
                }
            ]
        }
    ]
}