{
    "pages": [
        {
            "number": 1,
            "labels": [
                {
                    "top": 42,
                    "left": 57,
                    "width": 104,
                    "height": 7,
                    "tag_type": "TITLE"
                },
                {
                    "top": 42,
                    "left": 161,
                    "width": 80,
                    "height": 7,
                    "tag_type": "TITLE"
                },
                {
                    "top": 42,
                    "left": 240,
                    "width": 16,
                    "height": 7,
                    "tag_type": "TITLE"
                },
                {
                    "top": 735,
                    "left": 18,
                    "width": 19,
                    "height": 8,
                    "tag_type": "TEXT"
                },
                {
                    "top": 85,
                    "left": 57,
                    "width": 240,
                    "height": 9,
                    "tag_type": "TEXT"
                },
                {
                    "top": 97,
                    "left": 57,
                    "width": 240,
                    "height": 9,
                    "tag_type": "TEXT"
                },
                {
                    "top": 109,
                    "left": 57,
                    "width": 240,
                    "height": 9,
                    "tag_type": "TEXT"
                },
                {
                    "top": 120,
                    "left": 57,
                    "width": 240,
                    "height": 9,
                    "tag_type": "TEXT"
                },
                {
                    "top": 132,
                    "left": 57,
                    "width": 240,
                    "height": 9,
                    "tag_type": "TEXT"
                },
                {
                    "top": 144,
                    "left": 57,
                    "width": 240,
                    "height": 9,
                    "tag_type": "TEXT"
                },
                {
                    "top": 156,
                    "left": 57,
                    "width": 240,
                    "height": 9,
                    "tag_type": "TEXT"
                },
                {
                    "top": 167,
                    "left": 57,
                    "width": 240,
                    "height": 9,
                    "tag_type": "TEXT"
                },
                {
                    "top": 179,
                    "left": 57,
                    "width": 240,
                    "height": 9,
                    "tag_type": "TEXT"
                },
                {
                    "top": 191,
                    "left": 57,
                    "width": 241,
                    "height": 9,
                    "tag_type": "TEXT"
                },
                {
                    "top": 203,
                    "left": 57,
                    "width": 240,
                    "height": 9,
                    "tag_type": "TEXT"
                },
                {
                    "top": 214,
                    "left": 57,
                    "width": 240,
                    "height": 9,
                    "tag_type": "TEXT"
                },
                {
                    "top": 226,
                    "left": 57,
                    "width": 240,
                    "height": 9,
                    "tag_type": "TEXT"
                },
                {
                    "top": 238,
                    "left": 57,
                    "width": 241,
                    "height": 9,
                    "tag_type": "TEXT"
                },
                {
                    "top": 250,
                    "left": 57,
                    "width": 240,
                    "height": 9,
                    "tag_type": "TEXT"
                },
                {
                    "top": 261,
                    "left": 57,
                    "width": 241,
                    "height": 9,
                    "tag_type": "TEXT"
                },
                {
                    "top": 273,
                    "left": 57,
                    "width": 180,
                    "height": 9,
                    "tag_type": "TEXT"
                },
                {
                    "top": 270,
                    "left": 237,
                    "width": 4,
                    "height": 12,
                    "tag_type": "TEXT"
                },
                {
                    "top": 273,
                    "left": 240,
                    "width": 32,
                    "height": 9,
                    "tag_type": "TEXT"
                },
                {
                    "top": 270,
                    "left": 273,
                    "width": 4,
                    "height": 12,
                    "tag_type": "TEXT"
                },
                {
                    "top": 273,
                    "left": 277,
                    "width": 20,
                    "height": 9,
                    "tag_type": "TEXT"
                },
                {
                    "top": 285,
                    "left": 57,
                    "width": 241,
                    "height": 9,
                    "tag_type": "TEXT"
                },
                {
                    "top": 297,
                    "left": 57,
                    "width": 53,
                    "height": 9,
                    "tag_type": "TEXT"
                },
                {
                    "top": 320,
                    "left": 57,
                    "width": 121,
                    "height": 10,
                    "tag_type": "TITLE"
                },
                {
                    "top": 332,
                    "left": 57,
                    "width": 36,
                    "height": 8,
                    "tag_type": "TITLE"
                },
                {
                    "top": 344,
                    "left": 57,
                    "width": 240,
                    "height": 9,
                    "tag_type": "TEXT"
                },
                {
                    "top": 355,
                    "left": 57,
                    "width": 240,
                    "height": 9,
                    "tag_type": "TEXT"
                },
                {
                    "top": 367,
                    "left": 57,
                    "width": 240,
                    "height": 9,
                    "tag_type": "TEXT"
                },
                {
                    "top": 379,
                    "left": 57,
                    "width": 240,
                    "height": 9,
                    "tag_type": "TEXT"
                },
                {
                    "top": 391,
                    "left": 57,
                    "width": 240,
                    "height": 9,
                    "tag_type": "TEXT"
                },
                {
                    "top": 402,
                    "left": 57,
                    "width": 240,
                    "height": 9,
                    "tag_type": "TEXT"
                },
                {
                    "top": 414,
                    "left": 57,
                    "width": 240,
                    "height": 9,
                    "tag_type": "TEXT"
                },
                {
                    "top": 426,
                    "left": 57,
                    "width": 240,
                    "height": 9,
                    "tag_type": "TEXT"
                },
                {
                    "top": 438,
                    "left": 57,
                    "width": 241,
                    "height": 9,
                    "tag_type": "TEXT"
                },
                {
                    "top": 449,
                    "left": 57,
                    "width": 240,
                    "height": 9,
                    "tag_type": "TEXT"
                },
                {
                    "top": 461,
                    "left": 57,
                    "width": 240,
                    "height": 9,
                    "tag_type": "TEXT"
                },
                {
                    "top": 473,
                    "left": 57,
                    "width": 240,
                    "height": 9,
                    "tag_type": "TEXT"
                },
                {
                    "top": 485,
                    "left": 57,
                    "width": 240,
                    "height": 9,
                    "tag_type": "TEXT"
                },
                {
                    "top": 496,
                    "left": 57,
                    "width": 240,
                    "height": 9,
                    "tag_type": "TEXT"
                },
                {
                    "top": 508,
                    "left": 57,
                    "width": 240,
                    "height": 9,
                    "tag_type": "TEXT"
                },
                {
                    "top": 520,
                    "left": 57,
                    "width": 240,
                    "height": 9,
                    "tag_type": "TEXT"
                },
                {
                    "top": 532,
                    "left": 57,
                    "width": 240,
                    "height": 9,
                    "tag_type": "TEXT"
                },
                {
                    "top": 543,
                    "left": 57,
                    "width": 241,
                    "height": 9,
                    "tag_type": "TEXT"
                },
                {
                    "top": 555,
                    "left": 57,
                    "width": 241,
                    "height": 9,
                    "tag_type": "TEXT"
                },
                {
                    "top": 567,
                    "left": 57,
                    "width": 240,
                    "height": 9,
                    "tag_type": "TEXT"
                },
                {
                    "top": 579,
                    "left": 57,
                    "width": 240,
                    "height": 9,
                    "tag_type": "TEXT"
                },
                {
                    "top": 590,
                    "left": 57,
                    "width": 240,
                    "height": 9,
                    "tag_type": "TEXT"
                },
                {
                    "top": 602,
                    "left": 57,
                    "width": 136,
                    "height": 9,
                    "tag_type": "TEXT"
                },
                {
                    "top": 626,
                    "left": 57,
                    "width": 73,
                    "height": 8,
                    "tag_type": "TITLE"
                },
                {
                    "top": 637,
                    "left": 57,
                    "width": 240,
                    "height": 9,
                    "tag_type": "TEXT"
                },
                {
                    "top": 649,
                    "left": 57,
                    "width": 240,
                    "height": 9,
                    "tag_type": "TEXT"
                },
                {
                    "top": 661,
                    "left": 57,
                    "width": 240,
                    "height": 9,
                    "tag_type": "TEXT"
                },
                {
                    "top": 673,
                    "left": 57,
                    "width": 64,
                    "height": 9,
                    "tag_type": "TEXT"
                },
                {
                    "top": 696,
                    "left": 57,
                    "width": 19,
                    "height": 9,
                    "tag_type": "TITLE"
                },
                {
                    "top": 708,
                    "left": 57,
                    "width": 240,
                    "height": 9,
                    "tag_type": "TEXT"
                },
                {
                    "top": 720,
                    "left": 57,
                    "width": 240,
                    "height": 9,
                    "tag_type": "TEXT"
                },
                {
                    "top": 85,
                    "left": 315,
                    "width": 240,
                    "height": 9,
                    "tag_type": "TEXT"
                },
                {
                    "top": 97,
                    "left": 315,
                    "width": 241,
                    "height": 9,
                    "tag_type": "TEXT"
                },
                {
                    "top": 109,
                    "left": 315,
                    "width": 240,
                    "height": 9,
                    "tag_type": "TEXT"
                },
                {
                    "top": 120,
                    "left": 315,
                    "width": 241,
                    "height": 9,
                    "tag_type": "TEXT"
                },
                {
                    "top": 132,
                    "left": 315,
                    "width": 240,
                    "height": 9,
                    "tag_type": "TEXT"
                },
                {
                    "top": 144,
                    "left": 315,
                    "width": 241,
                    "height": 9,
                    "tag_type": "TEXT"
                },
                {
                    "top": 156,
                    "left": 315,
                    "width": 241,
                    "height": 9,
                    "tag_type": "TEXT"
                },
                {
                    "top": 167,
                    "left": 315,
                    "width": 241,
                    "height": 9,
                    "tag_type": "TEXT"
                },
                {
                    "top": 179,
                    "left": 315,
                    "width": 240,
                    "height": 9,
                    "tag_type": "TEXT"
                },
                {
                    "top": 191,
                    "left": 315,
                    "width": 241,
                    "height": 9,
                    "tag_type": "TEXT"
                },
                {
                    "top": 203,
                    "left": 315,
                    "width": 240,
                    "height": 9,
                    "tag_type": "TEXT"
                },
                {
                    "top": 214,
                    "left": 315,
                    "width": 50,
                    "height": 9,
                    "tag_type": "TEXT"
                },
                {
                    "top": 238,
                    "left": 315,
                    "width": 10,
                    "height": 9,
                    "tag_type": "TITLE"
                },
                {
                    "top": 234,
                    "left": 325,
                    "width": 4,
                    "height": 12,
                    "tag_type": "TITLE"
                },
                {
                    "top": 238,
                    "left": 329,
                    "width": 99,
                    "height": 9,
                    "tag_type": "TITLE"
                },
                {
                    "top": 250,
                    "left": 315,
                    "width": 241,
                    "height": 9,
                    "tag_type": "TEXT"
                },
                {
                    "top": 261,
                    "left": 315,
                    "width": 241,
                    "height": 9,
                    "tag_type": "TEXT"
                },
                {
                    "top": 273,
                    "left": 315,
                    "width": 64,
                    "height": 9,
                    "tag_type": "TEXT"
                },
                {
                    "top": 297,
                    "left": 315,
                    "width": 57,
                    "height": 9,
                    "tag_type": "TITLE"
                },
                {
                    "top": 293,
                    "left": 373,
                    "width": 4,
                    "height": 12,
                    "tag_type": "TITLE"
                },
                {
                    "top": 297,
                    "left": 377,
                    "width": 101,
                    "height": 9,
                    "tag_type": "TITLE"
                },
                {
                    "top": 308,
                    "left": 315,
                    "width": 241,
                    "height": 9,
                    "tag_type": "TEXT"
                },
                {
                    "top": 320,
                    "left": 315,
                    "width": 165,
                    "height": 9,
                    "tag_type": "TEXT"
                },
                {
                    "top": 344,
                    "left": 315,
                    "width": 103,
                    "height": 9,
                    "tag_type": "TITLE"
                },
                {
                    "top": 355,
                    "left": 315,
                    "width": 240,
                    "height": 9,
                    "tag_type": "TEXT"
                },
                {
                    "top": 367,
                    "left": 315,
                    "width": 241,
                    "height": 9,
                    "tag_type": "TEXT"
                },
                {
                    "top": 379,
                    "left": 315,
                    "width": 241,
                    "height": 9,
                    "tag_type": "TEXT"
                },
                {
                    "top": 391,
                    "left": 315,
                    "width": 240,
                    "height": 9,
                    "tag_type": "TEXT"
                },
                {
                    "top": 402,
                    "left": 315,
                    "width": 241,
                    "height": 9,
                    "tag_type": "TEXT"
                },
                {
                    "top": 414,
                    "left": 315,
                    "width": 240,
                    "height": 9,
                    "tag_type": "TEXT"
                },
                {
                    "top": 426,
                    "left": 315,
                    "width": 240,
                    "height": 9,
                    "tag_type": "TEXT"
                },
                {
                    "top": 438,
                    "left": 315,
                    "width": 240,
                    "height": 9,
                    "tag_type": "TEXT"
                },
                {
                    "top": 449,
                    "left": 315,
                    "width": 241,
                    "height": 9,
                    "tag_type": "TEXT"
                },
                {
                    "top": 461,
                    "left": 315,
                    "width": 240,
                    "height": 9,
                    "tag_type": "TEXT"
                },
                {
                    "top": 473,
                    "left": 315,
                    "width": 240,
                    "height": 9,
                    "tag_type": "TEXT"
                },
                {
                    "top": 485,
                    "left": 315,
                    "width": 241,
                    "height": 9,
                    "tag_type": "TEXT"
                },
                {
                    "top": 496,
                    "left": 315,
                    "width": 241,
                    "height": 9,
                    "tag_type": "TEXT"
                },
                {
                    "top": 508,
                    "left": 315,
                    "width": 240,
                    "height": 9,
                    "tag_type": "TEXT"
                },
                {
                    "top": 520,
                    "left": 315,
                    "width": 240,
                    "height": 9,
                    "tag_type": "TEXT"
                },
                {
                    "top": 532,
                    "left": 315,
                    "width": 240,
                    "height": 9,
                    "tag_type": "TEXT"
                },
                {
                    "top": 543,
                    "left": 315,
                    "width": 240,
                    "height": 9,
                    "tag_type": "TEXT"
                },
                {
                    "top": 555,
                    "left": 315,
                    "width": 241,
                    "height": 9,
                    "tag_type": "TEXT"
                },
                {
                    "top": 567,
                    "left": 315,
                    "width": 241,
                    "height": 9,
                    "tag_type": "TEXT"
                },
                {
                    "top": 579,
                    "left": 315,
                    "width": 241,
                    "height": 9,
                    "tag_type": "TEXT"
                },
                {
                    "top": 590,
                    "left": 315,
                    "width": 122,
                    "height": 9,
                    "tag_type": "TEXT"
                },
                {
                    "top": 614,
                    "left": 315,
                    "width": 110,
                    "height": 9,
                    "tag_type": "TITLE"
                },
                {
                    "top": 626,
                    "left": 315,
                    "width": 240,
                    "height": 9,
                    "tag_type": "TEXT"
                },
                {
                    "top": 637,
                    "left": 315,
                    "width": 241,
                    "height": 9,
                    "tag_type": "TEXT"
                },
                {
                    "top": 649,
                    "left": 315,
                    "width": 142,
                    "height": 9,
                    "tag_type": "TEXT"
                },
                {
                    "top": 673,
                    "left": 315,
                    "width": 183,
                    "height": 9,
                    "tag_type": "TEXT"
                },
                {
                    "top": 696,
                    "left": 315,
                    "width": 141,
                    "height": 9,
                    "tag_type": "TEXT"
                }
            ]
        }
    ]
}