{
    "pages": [
        {
            "number": 1,
            "labels": [
                {
                    "top": 41,
                    "left": 55,
                    "width": 121,
                    "height": 10,
                    "tag_type": "TITLE"
                },
                {
                    "top": 41,
                    "left": 368,
                    "width": 186,
                    "height": 10,
                    "tag_type": "TEXT"
                },
                {
                    "top": 756,
                    "left": 508,
                    "width": 46,
                    "height": 10,
                    "tag_type": "TEXT"
                },
                {
                    "top": 769,
                    "left": 432,
                    "width": 122,
                    "height": 8,
                    "tag_type": "TEXT"
                },
                {
                    "top": 204,
                    "left": 55,
                    "width": 242,
                    "height": 9,
                    "tag_type": "TITLE"
                },
                {
                    "top": 216,
                    "left": 55,
                    "width": 109,
                    "height": 9,
                    "tag_type": "TITLE"
                },
                {
                    "top": 227,
                    "left": 55,
                    "width": 241,
                    "height": 10,
                    "tag_type": "TEXT"
                },
                {
                    "top": 239,
                    "left": 55,
                    "width": 241,
                    "height": 9,
                    "tag_type": "TEXT"
                },
                {
                    "top": 248,
                    "left": 55,
                    "width": 241,
                    "height": 12,
                    "tag_type": "TEXT"
                },
                {
                    "top": 263,
                    "left": 55,
                    "width": 241,
                    "height": 9,
                    "tag_type": "TEXT"
                },
                {
                    "top": 275,
                    "left": 55,
                    "width": 241,
                    "height": 9,
                    "tag_type": "TEXT"
                },
                {
                    "top": 286,
                    "left": 55,
                    "width": 241,
                    "height": 9,
                    "tag_type": "TEXT"
                },
                {
                    "top": 298,
                    "left": 55,
                    "width": 241,
                    "height": 9,
                    "tag_type": "TEXT"
                },
                {
                    "top": 310,
                    "left": 55,
                    "width": 222,
                    "height": 9,
                    "tag_type": "TEXT"
                },
                {
                    "top": 334,
                    "left": 55,
                    "width": 53,
                    "height": 10,
                    "tag_type": "TITLE"
                },
                {
                    "top": 345,
                    "left": 55,
                    "width": 241,
                    "height": 9,
                    "tag_type": "TEXT"
                },
                {
                    "top": 357,
                    "left": 55,
                    "width": 241,
                    "height": 9,
                    "tag_type": "TEXT"
                },
                {
                    "top": 369,
                    "left": 55,
                    "width": 241,
                    "height": 9,
                    "tag_type": "TEXT"
                },
                {
                    "top": 380,
                    "left": 55,
                    "width": 241,
                    "height": 9,
                    "tag_type": "TEXT"
                },
                {
                    "top": 392,
                    "left": 55,
                    "width": 241,
                    "height": 9,
                    "tag_type": "TEXT"
                },
                {
                    "top": 404,
                    "left": 55,
                    "width": 241,
                    "height": 9,
                    "tag_type": "TEXT"
                },
                {
                    "top": 416,
                    "left": 55,
                    "width": 241,
                    "height": 9,
                    "tag_type": "TEXT"
                },
                {
                    "top": 427,
                    "left": 55,
                    "width": 241,
                    "height": 9,
                    "tag_type": "TEXT"
                },
                {
                    "top": 439,
                    "left": 55,
                    "width": 241,
                    "height": 9,
                    "tag_type": "TEXT"
                },
                {
                    "top": 451,
                    "left": 55,
                    "width": 241,
                    "height": 9,
                    "tag_type": "TEXT"
                },
                {
                    "top": 463,
                    "left": 55,
                    "width": 241,
                    "height": 9,
                    "tag_type": "TEXT"
                },
                {
                    "top": 474,
                    "left": 55,
                    "width": 241,
                    "height": 9,
                    "tag_type": "TEXT"
                },
                {
                    "top": 486,
                    "left": 55,
                    "width": 241,
                    "height": 9,
                    "tag_type": "TEXT"
                },
                {
                    "top": 498,
                    "left": 55,
                    "width": 241,
                    "height": 9,
                    "tag_type": "TEXT"
                },
                {
                    "top": 510,
                    "left": 55,
                    "width": 241,
                    "height": 9,
                    "tag_type": "TEXT"
                },
                {
                    "top": 521,
                    "left": 55,
                    "width": 241,
                    "height": 9,
                    "tag_type": "TEXT"
                },
                {
                    "top": 533,
                    "left": 55,
                    "width": 241,
                    "height": 9,
                    "tag_type": "TEXT"
                },
                {
                    "top": 545,
                    "left": 55,
                    "width": 241,
                    "height": 9,
                    "tag_type": "TEXT"
                },
                {
                    "top": 557,
                    "left": 55,
                    "width": 241,
                    "height": 9,
                    "tag_type": "TEXT"
                },
                {
                    "top": 568,
                    "left": 55,
                    "width": 241,
                    "height": 9,
                    "tag_type": "TEXT"
                },
                {
                    "top": 204,
                    "left": 313,
                    "width": 241,
                    "height": 9,
                    "tag_type": "TEXT"
                },
                {
                    "top": 216,
                    "left": 313,
                    "width": 241,
                    "height": 9,
                    "tag_type": "TEXT"
                },
                {
                    "top": 228,
                    "left": 313,
                    "width": 241,
                    "height": 9,
                    "tag_type": "TEXT"
                },
                {
                    "top": 239,
                    "left": 313,
                    "width": 132,
                    "height": 9,
                    "tag_type": "TEXT"
                },
                {
                    "top": 262,
                    "left": 313,
                    "width": 241,
                    "height": 10,
                    "tag_type": "TEXT"
                },
                {
                    "top": 275,
                    "left": 313,
                    "width": 241,
                    "height": 9,
                    "tag_type": "TEXT"
                },
                {
                    "top": 286,
                    "left": 313,
                    "width": 241,
                    "height": 9,
                    "tag_type": "TEXT"
                },
                {
                    "top": 298,
                    "left": 313,
                    "width": 241,
                    "height": 9,
                    "tag_type": "TEXT"
                },
                {
                    "top": 310,
                    "left": 313,
                    "width": 241,
                    "height": 9,
                    "tag_type": "TEXT"
                },
                {
                    "top": 321,
                    "left": 313,
                    "width": 241,
                    "height": 10,
                    "tag_type": "TEXT"
                },
                {
                    "top": 333,
                    "left": 313,
                    "width": 241,
                    "height": 9,
                    "tag_type": "TEXT"
                },
                {
                    "top": 345,
                    "left": 313,
                    "width": 241,
                    "height": 9,
                    "tag_type": "TEXT"
                },
                {
                    "top": 357,
                    "left": 313,
                    "width": 241,
                    "height": 9,
                    "tag_type": "TEXT"
                },
                {
                    "top": 368,
                    "left": 313,
                    "width": 241,
                    "height": 10,
                    "tag_type": "TEXT"
                },
                {
                    "top": 380,
                    "left": 313,
                    "width": 241,
                    "height": 9,
                    "tag_type": "TEXT"
                },
                {
                    "top": 392,
                    "left": 313,
                    "width": 241,
                    "height": 9,
                    "tag_type": "TEXT"
                },
                {
                    "top": 403,
                    "left": 313,
                    "width": 241,
                    "height": 10,
                    "tag_type": "TEXT"
                },
                {
                    "top": 416,
                    "left": 313,
                    "width": 241,
                    "height": 9,
                    "tag_type": "TEXT"
                },
                {
                    "top": 427,
                    "left": 313,
                    "width": 241,
                    "height": 9,
                    "tag_type": "TEXT"
                },
                {
                    "top": 439,
                    "left": 313,
                    "width": 30,
                    "height": 9,
                    "tag_type": "TEXT"
                },
                {
                    "top": 463,
                    "left": 313,
                    "width": 241,
                    "height": 9,
                    "tag_type": "TEXT"
                },
                {
                    "top": 474,
                    "left": 313,
                    "width": 242,
                    "height": 9,
                    "tag_type": "TEXT"
                },
                {
                    "top": 486,
                    "left": 313,
                    "width": 241,
                    "height": 9,
                    "tag_type": "TEXT"
                },
                {
                    "top": 497,
                    "left": 313,
                    "width": 241,
                    "height": 10,
                    "tag_type": "TEXT"
                },
                {
                    "top": 509,
                    "left": 313,
                    "width": 241,
                    "height": 10,
                    "tag_type": "TEXT"
                },
                {
                    "top": 521,
                    "left": 313,
                    "width": 241,
                    "height": 9,
                    "tag_type": "TEXT"
                },
                {
                    "top": 533,
                    "left": 313,
                    "width": 241,
                    "height": 9,
                    "tag_type": "TEXT"
                },
                {
                    "top": 544,
                    "left": 313,
                    "width": 241,
                    "height": 10,
                    "tag_type": "TEXT"
                },
                {
                    "top": 556,
                    "left": 313,
                    "width": 241,
                    "height": 10,
                    "tag_type": "TEXT"
                },
                {
                    "top": 568,
                    "left": 313,
                    "width": 241,
                    "height": 9,
                    "tag_type": "TEXT"
                },
                {
                    "top": 595,
                    "left": 55,
                    "width": 228,
                    "height": 7,
                    "tag_type": "TITLE"
                },
                {
                    "top": 613,
                    "left": 59,
                    "width": 15,
                    "height": 7,
                    "tag_type": "TABLE"
                },
                {
                    "top": 613,
                    "left": 283,
                    "width": 22,
                    "height": 7,
                    "tag_type": "TABLE"
                },
                {
                    "top": 613,
                    "left": 372,
                    "width": 22,
                    "height": 7,
                    "tag_type": "TABLE"
                },
                {
                    "top": 613,
                    "left": 466,
                    "width": 14,
                    "height": 7,
                    "tag_type": "TABLE"
                },
                {
                    "top": 635,
                    "left": 59,
                    "width": 14,
                    "height": 7,
                    "tag_type": "TABLE"
                },
                {
                    "top": 635,
                    "left": 283,
                    "width": 8,
                    "height": 7,
                    "tag_type": "TABLE"
                },
                {
                    "top": 635,
                    "left": 372,
                    "width": 8,
                    "height": 7,
                    "tag_type": "TABLE"
                },
                {
                    "top": 635,
                    "left": 466,
                    "width": 8,
                    "height": 7,
                    "tag_type": "TABLE"
                },
                {
                    "top": 643,
                    "left": 59,
                    "width": 104,
                    "height": 10,
                    "tag_type": "TABLE"
                },
                {
                    "top": 645,
                    "left": 283,
                    "width": 50,
                    "height": 7,
                    "tag_type": "TABLE"
                },
                {
                    "top": 645,
                    "left": 372,
                    "width": 57,
                    "height": 7,
                    "tag_type": "TABLE"
                },
                {
                    "top": 645,
                    "left": 466,
                    "width": 55,
                    "height": 7,
                    "tag_type": "TABLE"
                },
                {
                    "top": 655,
                    "left": 59,
                    "width": 147,
                    "height": 8,
                    "tag_type": "TABLE"
                },
                {
                    "top": 656,
                    "left": 283,
                    "width": 42,
                    "height": 7,
                    "tag_type": "TABLE"
                },
                {
                    "top": 656,
                    "left": 372,
                    "width": 47,
                    "height": 7,
                    "tag_type": "TABLE"
                },
                {
                    "top": 656,
                    "left": 466,
                    "width": 51,
                    "height": 7,
                    "tag_type": "TABLE"
                },
                {
                    "top": 663,
                    "left": 59,
                    "width": 95,
                    "height": 10,
                    "tag_type": "TABLE"
                },
                {
                    "top": 666,
                    "left": 283,
                    "width": 54,
                    "height": 7,
                    "tag_type": "TABLE"
                },
                {
                    "top": 666,
                    "left": 372,
                    "width": 48,
                    "height": 7,
                    "tag_type": "TABLE"
                },
                {
                    "top": 666,
                    "left": 466,
                    "width": 52,
                    "height": 7,
                    "tag_type": "TABLE"
                },
                {
                    "top": 676,
                    "left": 59,
                    "width": 141,
                    "height": 7,
                    "tag_type": "TABLE"
                },
                {
                    "top": 676,
                    "left": 283,
                    "width": 42,
                    "height": 7,
                    "tag_type": "TABLE"
                },
                {
                    "top": 676,
                    "left": 372,
                    "width": 42,
                    "height": 7,
                    "tag_type": "TABLE"
                },
                {
                    "top": 676,
                    "left": 466,
                    "width": 42,
                    "height": 7,
                    "tag_type": "TABLE"
                },
                {
                    "top": 698,
                    "left": 59,
                    "width": 489,
                    "height": 7,
                    "tag_type": "TEXT"
                },
                {
                    "top": 708,
                    "left": 59,
                    "width": 443,
                    "height": 7,
                    "tag_type": "TEXT"
                },
                {
                    "top": 87,
                    "left": 55,
                    "width": 168,
                    "height": 7,
                    "tag_type": "TITLE"
                },
                {
                    "top": 105,
                    "left": 59,
                    "width": 33,
                    "height": 7,
                    "tag_type": "TABLE"
                },
                {
                    "top": 105,
                    "left": 118,
                    "width": 14,
                    "height": 7,
                    "tag_type": "TABLE"
                },
                {
                    "top": 102,
                    "left": 151,
                    "width": 118,
                    "height": 10,
                    "tag_type": "TABLE"
                },
                {
                    "top": 105,
                    "left": 329,
                    "width": 154,
                    "height": 7,
                    "tag_type": "TABLE"
                },
                {
                    "top": 127,
                    "left": 59,
                    "width": 22,
                    "height": 7,
                    "tag_type": "TABLE"
                },
                {
                    "top": 127,
                    "left": 119,
                    "width": 8,
                    "height": 7,
                    "tag_type": "TABLE"
                },
                {
                    "top": 127,
                    "left": 151,
                    "width": 56,
                    "height": 7,
                    "tag_type": "TABLE"
                },
                {
                    "top": 127,
                    "left": 329,
                    "width": 44,
                    "height": 7,
                    "tag_type": "TABLE"
                },
                {
                    "top": 137,
                    "left": 59,
                    "width": 22,
                    "height": 7,
                    "tag_type": "TABLE"
                },
                {
                    "top": 137,
                    "left": 119,
                    "width": 8,
                    "height": 7,
                    "tag_type": "TABLE"
                },
                {
                    "top": 137,
                    "left": 151,
                    "width": 56,
                    "height": 7,
                    "tag_type": "TABLE"
                },
                {
                    "top": 137,
                    "left": 329,
                    "width": 48,
                    "height": 7,
                    "tag_type": "TABLE"
                },
                {
                    "top": 148,
                    "left": 59,
                    "width": 16,
                    "height": 7,
                    "tag_type": "TABLE"
                },
                {
                    "top": 148,
                    "left": 119,
                    "width": 8,
                    "height": 7,
                    "tag_type": "TABLE"
                },
                {
                    "top": 148,
                    "left": 151,
                    "width": 56,
                    "height": 7,
                    "tag_type": "TABLE"
                },
                {
                    "top": 148,
                    "left": 329,
                    "width": 48,
                    "height": 7,
                    "tag_type": "TABLE"
                },
                {
                    "top": 170,
                    "left": 59,
                    "width": 393,
                    "height": 7,
                    "tag_type": "TEXT"
                }
            ]
        }
    ]
}