{
    "pages": [
        {
            "number": 1,
            "labels": [
                {
                    "top": 480,
                    "left": 96,
                    "width": 2113,
                    "height": 822,
                    "token_type": "PARAGRAPH"
                },
                {
                    "top": 37,
                    "left": 84,
                    "width": 292,
                    "height": 51,
                    "token_type": "PARAGRAPH"
                },
                {
                    "top": 366,
                    "left": 779,
                    "width": 467,
                    "height": 127,
                    "token_type": "PARAGRAPH"
                },
                {
                    "top": 1604,
                    "left": 451,
                    "width": 687,
                    "height": 373,
                    "token_type": "PARAGRAPH"
                },
                {
                    "top": 1973,
                    "left": 453,
                    "width": 685,
                    "height": 464,
                    "token_type": "PARAGRAPH"
                },
                {
                    "top": 2434,
                    "left": 454,
                    "width": 685,
                    "height": 372,
                    "token_type": "PARAGRAPH"
                },
                {
                    "top": 2974,
                    "left": 163,
                    "width": 588,
                    "height": 50,
                    "token_type": "PARAGRAPH"
                },
                {
                    "top": 1328,
                    "left": 1462,
                    "width": 386,
                    "height": 66,
                    "token_type": "PARAGRAPH"
                },
                {
                    "top": 1606,
                    "left": 1176,
                    "width": 686,
                    "height": 186,
                    "token_type": "PARAGRAPH"
                },
                {
                    "top": 1788,
                    "left": 1180,
                    "width": 682,
                    "height": 695,
                    "token_type": "PARAGRAPH"
                },
                {
                    "top": 2480,
                    "left": 1182,
                    "width": 681,
                    "height": 323,
                    "token_type": "PARAGRAPH"
                },
                {
                    "top": 1249,
                    "left": 606,
                    "width": 1601,
                    "height": 84,
                    "token_type": "PARAGRAPH"
                },
                {
                    "top": 2976,
                    "left": 1840,
                    "width": 367,
                    "height": 43,
                    "token_type": "PARAGRAPH"
                },
                {
                    "top": 2545,
                    "left": 2263,
                    "width": 1,
                    "height": 389,
                    "token_type": "PARAGRAPH"
                }
            ]
        }
    ]
}