{
    "pages": [
        {
            "number": 1,
            "labels": [
                {
                    "top": 308,
                    "left": 122,
                    "width": 204,
                    "height": 67,
                    "token_type": "PARAGRAPH"
                }
            ]
        },
        {
            "number": 5,
            "labels": [
                {
                    "top": 376,
                    "left": 87,
                    "width": 420,
                    "height": 56,
                    "token_type": "PARAGRAPH"
                },
                {
                    "top": 540,
                    "left": 87,
                    "width": 420,
                    "height": 44,
                    "token_type": "PARAGRAPH"
                }
            ]
        },
        {
            "number": 6,
            "labels": [
                {
                    "top": 341,
                    "left": 87,
                    "width": 420,
                    "height": 56,
                    "token_type": "PARAGRAPH"
                }
            ]
        },
        {
            "number": 7,
            "labels": [
                {
                    "top": 609,
                    "left": 87,
                    "width": 420,
                    "height": 33,
                    "token_type": "PARAGRAPH"
                }
            ]
        },
        {
            "number": 8,
            "labels": [
                {
                    "top": 341,
                    "left": 87,
                    "width": 420,
                    "height": 103,
                    "token_type": "PARAGRAPH"
                },
                {
                    "top": 458,
                    "left": 87,
                    "width": 420,
                    "height": 126,
                    "token_type": "PARAGRAPH"
                },
                {
                    "top": 645,
                    "left": 87,
                    "width": 420,
                    "height": 68,
                    "token_type": "PARAGRAPH"
                }
            ]
        },
        {
            "number": 17,
            "labels": [
                {
                    "top": 349,
                    "left": 87,
                    "width": 420,
                    "height": 91,
                    "token_type": "PARAGRAPH"
                }
            ]
        },
        {
            "number": 23,
            "labels": [
                {
                    "top": 528,
                    "left": 87,
                    "width": 420,
                    "height": 33,
                    "token_type": "PARAGRAPH"
                }
            ]
        },
        {
            "number": 24,
            "labels": [
                {
                    "top": 353,
                    "left": 87,
                    "width": 420,
                    "height": 21,
                    "token_type": "PARAGRAPH"
                },
                {
                    "top": 563,
                    "left": 226,
                    "width": 142,
                    "height": 21,
                    "token_type": "PARAGRAPH"
                }
            ]
        },
        {
            "number": 25,
            "labels": [
                {
                    "top": 108,
                    "left": 349,
                    "width": 142,
                    "height": 21,
                    "token_type": "PARAGRAPH"
                }
            ]
        }
    ]
}