{
    "pages": [
        {
            "number": 1,
            "labels": [
                {
                    "top": 41,
                    "left": 55,
                    "width": 161,
                    "height": 10,
                    "label_type": 0
                },
                {
                    "top": 41,
                    "left": 328,
                    "width": 226,
                    "height": 10,
                    "label_type": 0
                },
                {
                    "top": 756,
                    "left": 508,
                    "width": 46,
                    "height": 10,
                    "label_type": 0
                },
                {
                    "top": 769,
                    "left": 432,
                    "width": 122,
                    "height": 8,
                    "label_type": 0
                },
                {
                    "top": 451,
                    "left": 55,
                    "width": 241,
                    "height": 256,
                    "label_type": 0
                },
                {
                    "top": 451,
                    "left": 313,
                    "width": 166,
                    "height": 9,
                    "label_type": 0
                },
                {
                    "top": 463,
                    "left": 313,
                    "width": 241,
                    "height": 197,
                    "label_type": 0
                },
                {
                    "top": 674,
                    "left": 313,
                    "width": 240,
                    "height": 21,
                    "label_type": 0
                },
                {
                    "top": 698,
                    "left": 313,
                    "width": 241,
                    "height": 32,
                    "label_type": 0
                },
                {
                    "top": 349,
                    "left": 55,
                    "width": 238,
                    "height": 9,
                    "label_type": 0
                },
                {
                    "top": 360,
                    "left": 55,
                    "width": 499,
                    "height": 54,
                    "label_type": 0
                },
                {
                    "top": 96,
                    "left": 63,
                    "width": 481,
                    "height": 233,
                    "label_type": 0
                }
            ]
        }
    ]
}