{
    "pages": [
        {
            "number": 1,
            "labels": [
                {
                    "top": 247,
                    "left": 168,
                    "width": 496,
                    "height": 62,
                    "tag_type": "TEXT"
                },
                {
                    "top": 304,
                    "left": 168,
                    "width": 497,
                    "height": 57,
                    "tag_type": "TEXT"
                },
                {
                    "top": 352,
                    "left": 165,
                    "width": 499,
                    "height": 63,
                    "tag_type": "TEXT"
                },
                {
                    "top": 404,
                    "left": 167,
                    "width": 498,
                    "height": 63,
                    "tag_type": "TEXT"
                },
                {
                    "top": 457,
                    "left": 166,
                    "width": 498,
                    "height": 62,
                    "tag_type": "TEXT"
                },
                {
                    "top": 509,
                    "left": 166,
                    "width": 243,
                    "height": 63,
                    "tag_type": "TEXT"
                },
                {
                    "top": 565,
                    "left": 217,
                    "width": 446,
                    "height": 61,
                    "tag_type": "TEXT"
                },
                {
                    "top": 614,
                    "left": 167,
                    "width": 497,
                    "height": 62,
                    "tag_type": "TEXT"
                },
                {
                    "top": 665,
                    "left": 167,
                    "width": 498,
                    "height": 63,
                    "tag_type": "TEXT"
                },
                {
                    "top": 717,
                    "left": 165,
                    "width": 498,
                    "height": 63,
                    "tag_type": "TEXT"
                },
                {
                    "top": 768,
                    "left": 167,
                    "width": 498,
                    "height": 63,
                    "tag_type": "TEXT"
                },
                {
                    "top": 821,
                    "left": 166,
                    "width": 462,
                    "height": 62,
                    "tag_type": "TEXT"
                },
                {
                    "top": 872,
                    "left": 217,
                    "width": 446,
                    "height": 65,
                    "tag_type": "TEXT"
                },
                {
                    "top": 925,
                    "left": 166,
                    "width": 497,
                    "height": 63,
                    "tag_type": "TEXT"
                },
                {
                    "top": 978,
                    "left": 166,
                    "width": 498,
                    "height": 62,
                    "tag_type": "TEXT"
                },
                {
                    "top": 1030,
                    "left": 166,
                    "width": 500,
                    "height": 63,
                    "tag_type": "TEXT"
                },
                {
                    "top": 1084,
                    "left": 167,
                    "width": 500,
                    "height": 62,
                    "tag_type": "TEXT"
                },
                {
                    "top": 1135,
                    "left": 165,
                    "width": 968,
                    "height": 62,
                    "tag_type": "TEXT"
                },
                {
                    "top": 1186,
                    "left": 166,
                    "width": 965,
                    "height": 63,
                    "tag_type": "TEXT"
                },
                {
                    "top": 1238,
                    "left": 165,
                    "width": 969,
                    "height": 63,
                    "tag_type": "TEXT"
                },
                {
                    "top": 1290,
                    "left": 167,
                    "width": 966,
                    "height": 63,
                    "tag_type": "TEXT"
                },
                {
                    "top": 1343,
                    "left": 166,
                    "width": 966,
                    "height": 63,
                    "tag_type": "TEXT"
                },
                {
                    "top": 1397,
                    "left": 166,
                    "width": 973,
                    "height": 61,
                    "tag_type": "TEXT"
                },
                {
                    "top": 1450,
                    "left": 167,
                    "width": 967,
                    "height": 58,
                    "tag_type": "TEXT"
                },
                {
                    "top": 1499,
                    "left": 166,
                    "width": 966,
                    "height": 63,
                    "tag_type": "TEXT"
                },
                {
                    "top": 1556,
                    "left": 166,
                    "width": 522,
                    "height": 57,
                    "tag_type": "TEXT"
                },
                {
                    "top": 1604,
                    "left": 217,
                    "width": 916,
                    "height": 63,
                    "tag_type": "TEXT"
                },
                {
                    "top": 1657,
                    "left": 166,
                    "width": 966,
                    "height": 62,
                    "tag_type": "TEXT"
                },
                {
                    "top": 1711,
                    "left": 166,
                    "width": 967,
                    "height": 62,
                    "tag_type": "TEXT"
                },
                {
                    "top": 1760,
                    "left": 166,
                    "width": 965,
                    "height": 63,
                    "tag_type": "TEXT"
                },
                {
                    "top": 1813,
                    "left": 167,
                    "width": 966,
                    "height": 62,
                    "tag_type": "TEXT"
                },
                {
                    "top": 1864,
                    "left": 166,
                    "width": 967,
                    "height": 63,
                    "tag_type": "TEXT"
                },
                {
                    "top": 1917,
                    "left": 166,
                    "width": 967,
                    "height": 62,
                    "tag_type": "TEXT"
                },
                {
                    "top": 1967,
                    "left": 167,
                    "width": 967,
                    "height": 65,
                    "tag_type": "TEXT"
                },
                {
                    "top": 2019,
                    "left": 166,
                    "width": 967,
                    "height": 65,
                    "tag_type": "TEXT"
                },
                {
                    "top": 2075,
                    "left": 167,
                    "width": 241,
                    "height": 62,
                    "tag_type": "TEXT"
                },
                {
                    "top": 2127,
                    "left": 216,
                    "width": 917,
                    "height": 63,
                    "tag_type": "TEXT"
                },
                {
                    "top": 2178,
                    "left": 166,
                    "width": 967,
                    "height": 63,
                    "tag_type": "TEXT"
                },
                {
                    "top": 2232,
                    "left": 166,
                    "width": 967,
                    "height": 63,
                    "tag_type": "TEXT"
                },
                {
                    "top": 2282,
                    "left": 166,
                    "width": 968,
                    "height": 63,
                    "tag_type": "TEXT"
                },
                {
                    "top": 2337,
                    "left": 166,
                    "width": 967,
                    "height": 62,
                    "tag_type": "TEXT"
                },
                {
                    "top": 2387,
                    "left": 166,
                    "width": 967,
                    "height": 63,
                    "tag_type": "TEXT"
                },
                {
                    "top": 2441,
                    "left": 166,
                    "width": 967,
                    "height": 62,
                    "tag_type": "TEXT"
                },
                {
                    "top": 522,
                    "left": 771,
                    "width": 125,
                    "height": 34,
                    "tag_type": "FIGURE"
                },
                {
                    "top": 552,
                    "left": 760,
                    "width": 148,
                    "height": 32,
                    "tag_type": "FIGURE"
                },
                {
                    "top": 581,
                    "left": 775,
                    "width": 120,
                    "height": 32,
                    "tag_type": "FIGURE"
                },
                {
                    "top": 881,
                    "left": 946,
                    "width": 95,
                    "height": 35,
                    "tag_type": "FIGURE"
                },
                {
                    "top": 1012,
                    "left": 815,
                    "width": 325,
                    "height": 45,
                    "tag_type": "TEXT"
                },
                {
                    "top": 1049,
                    "left": 968,
                    "width": 171,
                    "height": 46,
                    "tag_type": "TEXT"
                },
                {
                    "top": 881,
                    "left": 1095,
                    "width": 99,
                    "height": 35,
                    "tag_type": "FIGURE"
                },
                {
                    "top": 909,
                    "left": 935,
                    "width": 269,
                    "height": 35,
                    "tag_type": "FIGURE"
                },
                {
                    "top": 247,
                    "left": 1713,
                    "width": 446,
                    "height": 61,
                    "tag_type": "TEXT"
                },
                {
                    "top": 302,
                    "left": 1714,
                    "width": 446,
                    "height": 58,
                    "tag_type": "TEXT"
                },
                {
                    "top": 351,
                    "left": 1713,
                    "width": 446,
                    "height": 62,
                    "tag_type": "TEXT"
                },
                {
                    "top": 403,
                    "left": 1714,
                    "width": 445,
                    "height": 63,
                    "tag_type": "TEXT"
                },
                {
                    "top": 455,
                    "left": 1714,
                    "width": 447,
                    "height": 63,
                    "tag_type": "TEXT"
                },
                {
                    "top": 508,
                    "left": 1713,
                    "width": 446,
                    "height": 63,
                    "tag_type": "TEXT"
                },
                {
                    "top": 561,
                    "left": 1714,
                    "width": 444,
                    "height": 62,
                    "tag_type": "TEXT"
                },
                {
                    "top": 613,
                    "left": 1714,
                    "width": 200,
                    "height": 62,
                    "tag_type": "TEXT"
                },
                {
                    "top": 663,
                    "left": 1765,
                    "width": 393,
                    "height": 65,
                    "tag_type": "TEXT"
                },
                {
                    "top": 717,
                    "left": 1714,
                    "width": 445,
                    "height": 61,
                    "tag_type": "TEXT"
                },
                {
                    "top": 767,
                    "left": 1714,
                    "width": 445,
                    "height": 63,
                    "tag_type": "TEXT"
                },
                {
                    "top": 819,
                    "left": 1714,
                    "width": 446,
                    "height": 62,
                    "tag_type": "TEXT"
                },
                {
                    "top": 871,
                    "left": 1713,
                    "width": 446,
                    "height": 63,
                    "tag_type": "TEXT"
                },
                {
                    "top": 924,
                    "left": 1714,
                    "width": 444,
                    "height": 63,
                    "tag_type": "TEXT"
                },
                {
                    "top": 977,
                    "left": 1714,
                    "width": 445,
                    "height": 62,
                    "tag_type": "TEXT"
                },
                {
                    "top": 1035,
                    "left": 1186,
                    "width": 973,
                    "height": 55,
                    "tag_type": "TEXT"
                },
                {
                    "top": 1089,
                    "left": 1186,
                    "width": 972,
                    "height": 54,
                    "tag_type": "TEXT"
                },
                {
                    "top": 1133,
                    "left": 1190,
                    "width": 970,
                    "height": 63,
                    "tag_type": "TEXT"
                },
                {
                    "top": 1186,
                    "left": 1186,
                    "width": 980,
                    "height": 63,
                    "tag_type": "TEXT"
                },
                {
                    "top": 1237,
                    "left": 1187,
                    "width": 973,
                    "height": 63,
                    "tag_type": "TEXT"
                },
                {
                    "top": 1290,
                    "left": 1187,
                    "width": 973,
                    "height": 62,
                    "tag_type": "TEXT"
                },
                {
                    "top": 1342,
                    "left": 1186,
                    "width": 974,
                    "height": 62,
                    "tag_type": "TEXT"
                },
                {
                    "top": 1393,
                    "left": 1186,
                    "width": 974,
                    "height": 63,
                    "tag_type": "TEXT"
                },
                {
                    "top": 1445,
                    "left": 1187,
                    "width": 973,
                    "height": 65,
                    "tag_type": "TEXT"
                },
                {
                    "top": 1499,
                    "left": 1186,
                    "width": 515,
                    "height": 62,
                    "tag_type": "TEXT"
                },
                {
                    "top": 629,
                    "left": 1220,
                    "width": 70,
                    "height": 32,
                    "tag_type": "FIGURE"
                },
                {
                    "top": 658,
                    "left": 1219,
                    "width": 193,
                    "height": 32,
                    "tag_type": "FIGURE"
                },
                {
                    "top": 761,
                    "left": 1246,
                    "width": 77,
                    "height": 32,
                    "tag_type": "FIGURE"
                },
                {
                    "top": 784,
                    "left": 1231,
                    "width": 108,
                    "height": 35,
                    "tag_type": "FIGURE"
                },
                {
                    "top": 810,
                    "left": 1248,
                    "width": 73,
                    "height": 34,
                    "tag_type": "FIGURE"
                },
                {
                    "top": 1602,
                    "left": 1712,
                    "width": 449,
                    "height": 65,
                    "tag_type": "TEXT"
                },
                {
                    "top": 1655,
                    "left": 1712,
                    "width": 448,
                    "height": 63,
                    "tag_type": "TEXT"
                },
                {
                    "top": 1714,
                    "left": 1711,
                    "width": 447,
                    "height": 55,
                    "tag_type": "TEXT"
                },
                {
                    "top": 1760,
                    "left": 1712,
                    "width": 448,
                    "height": 62,
                    "tag_type": "TEXT"
                },
                {
                    "top": 1811,
                    "left": 1711,
                    "width": 448,
                    "height": 63,
                    "tag_type": "TEXT"
                },
                {
                    "top": 1865,
                    "left": 1711,
                    "width": 448,
                    "height": 61,
                    "tag_type": "TEXT"
                },
                {
                    "top": 1914,
                    "left": 1186,
                    "width": 974,
                    "height": 63,
                    "tag_type": "TEXT"
                },
                {
                    "top": 1974,
                    "left": 1187,
                    "width": 972,
                    "height": 54,
                    "tag_type": "TEXT"
                },
                {
                    "top": 2020,
                    "left": 1186,
                    "width": 971,
                    "height": 63,
                    "tag_type": "TEXT"
                },
                {
                    "top": 2072,
                    "left": 1184,
                    "width": 977,
                    "height": 63,
                    "tag_type": "TEXT"
                },
                {
                    "top": 2124,
                    "left": 1186,
                    "width": 974,
                    "height": 63,
                    "tag_type": "TEXT"
                },
                {
                    "top": 2178,
                    "left": 1185,
                    "width": 974,
                    "height": 62,
                    "tag_type": "TEXT"
                },
                {
                    "top": 2234,
                    "left": 1186,
                    "width": 972,
                    "height": 58,
                    "tag_type": "TEXT"
                },
                {
                    "top": 2282,
                    "left": 1186,
                    "width": 974,
                    "height": 63,
                    "tag_type": "TEXT"
                },
                {
                    "top": 2334,
                    "left": 1185,
                    "width": 974,
                    "height": 62,
                    "tag_type": "TEXT"
                },
                {
                    "top": 2392,
                    "left": 1186,
                    "width": 366,
                    "height": 54,
                    "tag_type": "TEXT"
                },
                {
                    "top": 2438,
                    "left": 1234,
                    "width": 925,
                    "height": 62,
                    "tag_type": "TEXT"
                },
                {
                    "top": 2582,
                    "left": 395,
                    "width": 1526,
                    "height": 115,
                    "tag_type": "TEXT"
                },
                {
                    "top": 2686,
                    "left": 281,
                    "width": 1758,
                    "height": 124,
                    "tag_type": "TEXT"
                },
                {
                    "top": 2786,
                    "left": 405,
                    "width": 1504,
                    "height": 135,
                    "tag_type": "TEXT"
                },
                {
                    "top": 2891,
                    "left": 568,
                    "width": 1175,
                    "height": 138,
                    "tag_type": "TEXT"
                },
                {
                    "top": 3143,
                    "left": 1383,
                    "width": 677,
                    "height": 42,
                    "tag_type": "TEXT"
                },
                {
                    "top": 3143,
                    "left": 2107,
                    "width": 39,
                    "height": 42,
                    "tag_type": "TEXT"
                }
            ]
        }
    ]
}