{
    "pages": [
        {
            "number": 1,
            "labels": [
                {
                    "top": 44,
                    "left": 508,
                    "width": 67,
                    "height": 9,
                    "tag_type": "TITLE"
                },
                {
                    "top": 756,
                    "left": 508,
                    "width": 46,
                    "height": 10,
                    "tag_type": "TEXT"
                },
                {
                    "top": 769,
                    "left": 432,
                    "width": 122,
                    "height": 8,
                    "tag_type": "TEXT"
                },
                {
                    "top": 35,
                    "left": 55,
                    "width": 259,
                    "height": 23,
                    "tag_type": "TITLE"
                },
                {
                    "top": 86,
                    "left": 502,
                    "width": 79,
                    "height": 10,
                    "tag_type": "TITLE"
                },
                {
                    "top": 87,
                    "left": 55,
                    "width": 73,
                    "height": 13,
                    "tag_type": "TITLE"
                },
                {
                    "top": 105,
                    "left": 55,
                    "width": 272,
                    "height": 15,
                    "tag_type": "TITLE"
                },
                {
                    "top": 122,
                    "left": 55,
                    "width": 117,
                    "height": 14,
                    "tag_type": "TEXT"
                },
                {
                    "top": 158,
                    "left": 55,
                    "width": 309,
                    "height": 8,
                    "tag_type": "TEXT"
                },
                {
                    "top": 172,
                    "left": 55,
                    "width": 185,
                    "height": 8,
                    "tag_type": "TEXT"
                },
                {
                    "top": 184,
                    "left": 55,
                    "width": 92,
                    "height": 8,
                    "tag_type": "TEXT"
                },
                {
                    "top": 332,
                    "left": 112,
                    "width": 44,
                    "height": 10,
                    "tag_type": "TITLE"
                },
                {
                    "top": 347,
                    "left": 112,
                    "width": 386,
                    "height": 9,
                    "tag_type": "TEXT"
                },
                {
                    "top": 358,
                    "left": 112,
                    "width": 386,
                    "height": 9,
                    "tag_type": "TEXT"
                },
                {
                    "top": 370,
                    "left": 112,
                    "width": 386,
                    "height": 9,
                    "tag_type": "TEXT"
                },
                {
                    "top": 382,
                    "left": 112,
                    "width": 386,
                    "height": 9,
                    "tag_type": "TEXT"
                },
                {
                    "top": 394,
                    "left": 112,
                    "width": 385,
                    "height": 9,
                    "tag_type": "TEXT"
                },
                {
                    "top": 405,
                    "left": 112,
                    "width": 386,
                    "height": 9,
                    "tag_type": "TEXT"
                },
                {
                    "top": 417,
                    "left": 112,
                    "width": 386,
                    "height": 9,
                    "tag_type": "TEXT"
                },
                {
                    "top": 429,
                    "left": 112,
                    "width": 386,
                    "height": 9,
                    "tag_type": "TEXT"
                },
                {
                    "top": 441,
                    "left": 112,
                    "width": 386,
                    "height": 9,
                    "tag_type": "TEXT"
                },
                {
                    "top": 452,
                    "left": 112,
                    "width": 386,
                    "height": 9,
                    "tag_type": "TEXT"
                },
                {
                    "top": 464,
                    "left": 112,
                    "width": 125,
                    "height": 9,
                    "tag_type": "TEXT"
                },
                {
                    "top": 514,
                    "left": 55,
                    "width": 63,
                    "height": 10,
                    "tag_type": "TITLE"
                },
                {
                    "top": 525,
                    "left": 55,
                    "width": 241,
                    "height": 9,
                    "tag_type": "TEXT"
                },
                {
                    "top": 537,
                    "left": 55,
                    "width": 241,
                    "height": 9,
                    "tag_type": "TEXT"
                },
                {
                    "top": 548,
                    "left": 55,
                    "width": 241,
                    "height": 9,
                    "tag_type": "TEXT"
                },
                {
                    "top": 560,
                    "left": 55,
                    "width": 241,
                    "height": 9,
                    "tag_type": "TEXT"
                },
                {
                    "top": 572,
                    "left": 55,
                    "width": 241,
                    "height": 9,
                    "tag_type": "TEXT"
                },
                {
                    "top": 584,
                    "left": 55,
                    "width": 241,
                    "height": 9,
                    "tag_type": "TEXT"
                },
                {
                    "top": 596,
                    "left": 55,
                    "width": 241,
                    "height": 9,
                    "tag_type": "TEXT"
                },
                {
                    "top": 607,
                    "left": 55,
                    "width": 241,
                    "height": 9,
                    "tag_type": "TEXT"
                },
                {
                    "top": 619,
                    "left": 55,
                    "width": 241,
                    "height": 9,
                    "tag_type": "TEXT"
                },
                {
                    "top": 631,
                    "left": 55,
                    "width": 241,
                    "height": 9,
                    "tag_type": "TEXT"
                },
                {
                    "top": 643,
                    "left": 55,
                    "width": 241,
                    "height": 9,
                    "tag_type": "TEXT"
                },
                {
                    "top": 654,
                    "left": 55,
                    "width": 241,
                    "height": 9,
                    "tag_type": "TEXT"
                },
                {
                    "top": 666,
                    "left": 55,
                    "width": 241,
                    "height": 9,
                    "tag_type": "TEXT"
                },
                {
                    "top": 678,
                    "left": 55,
                    "width": 241,
                    "height": 9,
                    "tag_type": "TEXT"
                },
                {
                    "top": 689,
                    "left": 55,
                    "width": 160,
                    "height": 9,
                    "tag_type": "TEXT"
                },
                {
                    "top": 514,
                    "left": 313,
                    "width": 109,
                    "height": 10,
                    "tag_type": "TITLE"
                },
                {
                    "top": 525,
                    "left": 313,
                    "width": 241,
                    "height": 9,
                    "tag_type": "TEXT"
                },
                {
                    "top": 537,
                    "left": 313,
                    "width": 241,
                    "height": 9,
                    "tag_type": "TEXT"
                },
                {
                    "top": 548,
                    "left": 313,
                    "width": 241,
                    "height": 9,
                    "tag_type": "TEXT"
                },
                {
                    "top": 560,
                    "left": 313,
                    "width": 241,
                    "height": 9,
                    "tag_type": "TEXT"
                },
                {
                    "top": 572,
                    "left": 313,
                    "width": 241,
                    "height": 9,
                    "tag_type": "TEXT"
                },
                {
                    "top": 584,
                    "left": 313,
                    "width": 241,
                    "height": 9,
                    "tag_type": "TEXT"
                },
                {
                    "top": 596,
                    "left": 313,
                    "width": 241,
                    "height": 9,
                    "tag_type": "TEXT"
                },
                {
                    "top": 607,
                    "left": 313,
                    "width": 241,
                    "height": 9,
                    "tag_type": "TEXT"
                },
                {
                    "top": 619,
                    "left": 313,
                    "width": 133,
                    "height": 9,
                    "tag_type": "TEXT"
                },
                {
                    "top": 643,
                    "left": 313,
                    "width": 241,
                    "height": 9,
                    "tag_type": "TEXT"
                },
                {
                    "top": 654,
                    "left": 313,
                    "width": 241,
                    "height": 9,
                    "tag_type": "TEXT"
                },
                {
                    "top": 666,
                    "left": 313,
                    "width": 241,
                    "height": 9,
                    "tag_type": "TEXT"
                },
                {
                    "top": 678,
                    "left": 313,
                    "width": 241,
                    "height": 9,
                    "tag_type": "TEXT"
                },
                {
                    "top": 689,
                    "left": 313,
                    "width": 241,
                    "height": 9,
                    "tag_type": "TEXT"
                },
                {
                    "top": 701,
                    "left": 313,
                    "width": 241,
                    "height": 9,
                    "tag_type": "TEXT"
                },
                {
                    "top": 713,
                    "left": 313,
                    "width": 241,
                    "height": 9,
                    "tag_type": "TEXT"
                },
                {
                    "top": 725,
                    "left": 313,
                    "width": 241,
                    "height": 9,
                    "tag_type": "TEXT"
                },
                {
                    "top": 226,
                    "left": 55,
                    "width": 98,
                    "height": 7,
                    "tag_type": "TEXT"
                },
                {
                    "top": 241,
                    "left": 55,
                    "width": 94,
                    "height": 7,
                    "tag_type": "TEXT"
                },
                {
                    "top": 241,
                    "left": 158,
                    "width": 92,
                    "height": 7,
                    "tag_type": "TEXT"
                },
                {
                    "top": 226,
                    "left": 310,
                    "width": 97,
                    "height": 7,
                    "tag_type": "TEXT"
                },
                {
                    "top": 236,
                    "left": 310,
                    "width": 98,
                    "height": 7,
                    "tag_type": "TEXT"
                },
                {
                    "top": 255,
                    "left": 55,
                    "width": 248,
                    "height": 7,
                    "tag_type": "TEXT"
                },
                {
                    "top": 269,
                    "left": 55,
                    "width": 153,
                    "height": 7,
                    "tag_type": "TEXT"
                },
                {
                    "top": 279,
                    "left": 55,
                    "width": 492,
                    "height": 7,
                    "tag_type": "TEXT"
                },
                {
                    "top": 288,
                    "left": 55,
                    "width": 400,
                    "height": 7,
                    "tag_type": "TEXT"
                }
            ]
        }
    ]
}