{
    "pages": [
        {
            "number": 1,
            "labels": [
                {
                    "top": 42,
                    "left": 311,
                    "width": 245,
                    "height": 7,
                    "label_type": 0
                },
                {
                    "top": 735,
                    "left": 569,
                    "width": 19,
                    "height": 8,
                    "label_type": 0
                },
                {
                    "top": 389,
                    "left": 57,
                    "width": 241,
                    "height": 21,
                    "label_type": 0
                },
                {
                    "top": 424,
                    "left": 57,
                    "width": 238,
                    "height": 20,
                    "label_type": 0
                },
                {
                    "top": 448,
                    "left": 57,
                    "width": 241,
                    "height": 185,
                    "label_type": 0
                },
                {
                    "top": 647,
                    "left": 57,
                    "width": 236,
                    "height": 20,
                    "label_type": 0
                },
                {
                    "top": 670,
                    "left": 57,
                    "width": 241,
                    "height": 57,
                    "label_type": 0
                },
                {
                    "top": 388,
                    "left": 315,
                    "width": 241,
                    "height": 151,
                    "label_type": 0
                },
                {
                    "top": 553,
                    "left": 315,
                    "width": 189,
                    "height": 8,
                    "label_type": 0
                },
                {
                    "top": 565,
                    "left": 315,
                    "width": 241,
                    "height": 162,
                    "label_type": 0
                },
                {
                    "top": 85,
                    "left": 57,
                    "width": 31,
                    "height": 7,
                    "label_type": 0
                },
                {
                    "top": 343,
                    "left": 57,
                    "width": 494,
                    "height": 26,
                    "label_type": 0
                },
                {
                    "top": 210,
                    "left": 84,
                    "width": 287,
                    "height": 109,
                    "label_type": 0
                }
            ]
        }
    ]
}