{
    "pages": [
        {
            "number": 1,
            "labels": [
                {
                    "top": 41,
                    "left": 55,
                    "width": 195,
                    "height": 10,
                    "label_type": 0
                },
                {
                    "top": 41,
                    "left": 368,
                    "width": 186,
                    "height": 10,
                    "label_type": 0
                },
                {
                    "top": 756,
                    "left": 508,
                    "width": 46,
                    "height": 10,
                    "label_type": 0
                },
                {
                    "top": 769,
                    "left": 432,
                    "width": 122,
                    "height": 8,
                    "label_type": 0
                },
                {
                    "top": 86,
                    "left": 55,
                    "width": 241,
                    "height": 92,
                    "label_type": 0
                },
                {
                    "top": 192,
                    "left": 55,
                    "width": 241,
                    "height": 197,
                    "label_type": 0
                },
                {
                    "top": 404,
                    "left": 55,
                    "width": 241,
                    "height": 91,
                    "label_type": 0
                },
                {
                    "top": 510,
                    "left": 55,
                    "width": 241,
                    "height": 79,
                    "label_type": 0
                },
                {
                    "top": 604,
                    "left": 55,
                    "width": 43,
                    "height": 10,
                    "label_type": 0
                },
                {
                    "top": 616,
                    "left": 55,
                    "width": 82,
                    "height": 9,
                    "label_type": 0
                },
                {
                    "top": 627,
                    "left": 55,
                    "width": 242,
                    "height": 103,
                    "label_type": 0
                },
                {
                    "top": 87,
                    "left": 313,
                    "width": 241,
                    "height": 67,
                    "label_type": 0
                },
                {
                    "top": 169,
                    "left": 313,
                    "width": 199,
                    "height": 9,
                    "label_type": 0
                },
                {
                    "top": 181,
                    "left": 313,
                    "width": 241,
                    "height": 150,
                    "label_type": 0
                },
                {
                    "top": 345,
                    "left": 313,
                    "width": 223,
                    "height": 22,
                    "label_type": 0
                },
                {
                    "top": 369,
                    "left": 313,
                    "width": 242,
                    "height": 232,
                    "label_type": 0
                },
                {
                    "top": 616,
                    "left": 313,
                    "width": 98,
                    "height": 9,
                    "label_type": 0
                },
                {
                    "top": 627,
                    "left": 313,
                    "width": 241,
                    "height": 103,
                    "label_type": 0
                }
            ]
        }
    ]
}